MANIFEST.in
README.rst
requirements.txt
setup.cfg
setup.py
django_file_validator/__init__.py
django_file_validator/validators.py
django_file_validator.egg-info/PKG-INFO
django_file_validator.egg-info/SOURCES.txt
django_file_validator.egg-info/dependency_links.txt
django_file_validator.egg-info/entry_points.txt
django_file_validator.egg-info/not-zip-safe
django_file_validator.egg-info/requires.txt
django_file_validator.egg-info/top_level.txt
django_file_validator/locale/es/LC_MESSAGES/django.mo
django_file_validator/locale/es/LC_MESSAGES/django.po
django_file_validator/locale/pt_BR/LC_MESSAGES/django.mo
django_file_validator/locale/pt_BR/LC_MESSAGES/django.po