Metadata-Version: 1.1
Name: django-file-validator
Version: 0.0.7
Summary: Simple project to validate FileFields/ImageFields, like max size of uploaded files.
Home-page: https://github.com/adrianoveiga/django-file-validator.git
Author: Adriano Veiga
Author-email: profpardal.88@gmail.com
License: MIT
Keywords: django file validator max size upload
Platform: UNKNOWN
Classifier: Development Status :: 4 - Beta
Classifier: Intended Audience :: Developers
Classifier: Topic :: Software Development :: Libraries :: Python Modules
Classifier: Environment :: Web Environment
Classifier: Framework :: Django
Classifier: License :: OSI Approved :: MIT License
Classifier: Programming Language :: Python :: 2
Classifier: Programming Language :: Python :: 2.6
Classifier: Programming Language :: Python :: 2.7
